visual_tokenization/__init__.py
visual_tokenization/visual_tokenization.py
visuals_tokenization-0.1.2.dist-info/METADATA
visuals_tokenization-0.1.2.dist-info/WHEEL
visuals_tokenization-0.1.2.dist-info/top_level.txt
visuals_tokenization-0.1.2.dist-info/RECORD
