Metadata-Version: 2.1
Name: visuals-tokenization
Version: 0.1.2
Summary: Library to visualize different tokenization methords
Author: Marcel Tino
Author-email: <marceltino92@gmail.com>
Keywords: tokens,visual_tokenizations
Requires-Dist: numpy
Requires-Dist: pandas
Requires-Dist: nltk
Requires-Dist: spacy
Requires-Dist: gensim
Requires-Dist: transformers
Requires-Dist: beautifultable
